pydesktools/__init__.py
pydesktools/core.py
pydesktools/default.py
pydesktools/main.py
pydesktools-0.0.1.dist-info/LICENSE
pydesktools-0.0.1.dist-info/METADATA
pydesktools-0.0.1.dist-info/WHEEL
pydesktools-0.0.1.dist-info/top_level.txt
pydesktools-0.0.1.dist-info/RECORD
