Metadata-Version: 2.1
Name: pydesktools
Version: 0.0.1
Summary: Python Desktop Tool Box
Home-page: https://github.com/openHacking/PyDeskTools
Author: openHacking
Author-email: openHacking <openHacking@126.com>
License: The MIT License (MIT)        
Project-URL: Homepage, https://github.com/openHacking/PyDeskTools
Project-URL: Bug Tracker, https://github.com/openHacking/PyDeskTools/issues
Keywords: python,tool,desktop,GUI,tkinter,UI
Classifier: Development Status :: 3 - Alpha
Classifier: Intended Audience :: Developers
Classifier: Topic :: Software Development :: Build Tools
Classifier: Programming Language :: Python :: 3
Classifier: License :: OSI Approved :: MIT License
Classifier: Operating System :: OS Independent
Requires-Python: >=3.7
License-File: LICENSE
Requires-Dist: pydeskui (==0.0.1)
